{
  "_class": "shapePath",
  "booleanOperation": -1,
  "do_objectID": "685AED2A-1858-42D6-AC0E-06EF6928DB3F",
  "edited": true,
  "exportOptions": {
    "_class": "exportOptions",
    "exportFormats": [
    ],
    "includedLayerIds": [
    ],
    "layerOptions": 0,
    "shouldTrim": false
  },
  "frame": {
    "_class": "rect",
    "constrainProportions": false,
    "height": 37,
    "width": 299.375,
    "x": 0,
    "y": 0
  },
  "isFlippedHorizontal": false,
  "isFlippedVertical": false,
  "isLocked": false,
  "isVisible": true,
  "layerListExpandedType": 0,
  "name": "Path",
  "nameIsFixed": false,
  "path": {
    "_class": "path",
    "isClosed": true,
    "pointRadiusBehaviour": 1,
    "points": [
      {
        "_class": "curvePoint",
        "cornerRadius": 0,
        "curveFrom": "{0, 0}",
        "curveMode": 1,
        "curveTo": "{0, 0}",
        "hasCurveFrom": false,
        "hasCurveTo": false,
        "point": "{0, 0}"
      },
      {
        "_class": "curvePoint",
        "cornerRadius": 0,
        "curveFrom": "{0.94962839248434261, 0}",
        "curveMode": 1,
        "curveTo": "{0.94962839248434261, 0}",
        "hasCurveFrom": false,
        "hasCurveTo": false,
        "point": "{0.94962839248434261, 0}"
      },
      {
        "_class": "curvePoint",
        "cornerRadius": 0,
        "curveFrom": "{1, 0.5}",
        "curveMode": 1,
        "curveTo": "{1, 0.5}",
        "hasCurveFrom": false,
        "hasCurveTo": false,
        "point": "{1, 0.5}"
      },
      {
        "_class": "curvePoint",
        "cornerRadius": 0,
        "curveFrom": "{0.94979206680584571, 1}",
        "curveMode": 1,
        "curveTo": "{0.94979206680584571, 1}",
        "hasCurveFrom": false,
        "hasCurveTo": false,
        "point": "{0.94979206680584571, 1}"
      },
      {
        "_class": "curvePoint",
        "cornerRadius": 0,
        "curveFrom": "{0.00069478079331931517, 1}",
        "curveMode": 1,
        "curveTo": "{0.00069478079331931517, 1}",
        "hasCurveFrom": false,
        "hasCurveTo": false,
        "point": "{0.00069478079331931517, 1}"
      },
      {
        "_class": "curvePoint",
        "cornerRadius": 0,
        "curveFrom": "{0.05065887265135717, 0.49983783783783858}",
        "curveMode": 1,
        "curveTo": "{0.05065887265135717, 0.49983783783783858}",
        "hasCurveFrom": false,
        "hasCurveTo": false,
        "point": "{0.05065887265135717, 0.49983783783783858}"
      }
    ]
  },
  "resizingConstraint": 63,
  "resizingType": 0,
  "rotation": 0,
  "shouldBreakMaskChain": false
}